{
  "project_info": {
    "project_number": "694718347026",
    "firebase_url": "https://flickering-inferno-2585.firebaseio.com",
    "project_id": "flickering-inferno-2585",
    "storage_bucket": "flickering-inferno-2585.appspot.com"
  },
  "client": [
    {
      "client_info": {
        "mobilesdk_app_id": "1:694718347026:android:94edb95f47f7f068",
        "android_client_info": {
          "package_name": "mavlana.halaleats"
        }
      },
      "oauth_client": [
        {
          "client_id": "694718347026-s5o1lopk0er4idbkakc89had8qnlru8g.apps.googleusercontent.com",
          "client_type": 3
        }
      ],
      "api_key": [
        {
          "current_key": "AIzaSyCr4zubGVR7hMCS-TpKeVMg-Lbb9oTLQcQ"
        }
      ],
      "services": {
        "analytics_service": {
          "status": 1
        },
        "appinvite_service": {
          "status": 1,
          "other_platform_oauth_client": []
        },
        "ads_service": {
          "status": 2
        }
      }
    }
  ],
  "configuration_version": "1"
}